enkaliprime_cli/__init__.py
enkaliprime_cli/banner.py
enkaliprime_cli/code_utils.py
enkaliprime_cli/coder.py
enkaliprime_cli/config.jsonc
enkaliprime_cli/main.py
enkaliprime_cli/menu.py
enkaliprime_cli/ui.py
enkaliprime_cli/commands/__init__.py
enkaliprime_cli/commands/chat.py
enkaliprime_cli/commands/config.py
enkaliprime_cli/commands/session.py
enkaliprime_cli-0.11.6.dist-info/licenses/LICENSE
enkaliprime_cli-0.11.6.dist-info/METADATA
enkaliprime_cli-0.11.6.dist-info/WHEEL
enkaliprime_cli-0.11.6.dist-info/entry_points.txt
enkaliprime_cli-0.11.6.dist-info/top_level.txt
enkaliprime_cli-0.11.6.dist-info/RECORD
