Metadata-Version: 2.4
Name: enkaliprime-cli
Version: 0.11.6
Summary: Command-line interface for EnkaliPrime Chat API
Author-email: EnkaliPrime <support@enkaliprime.com>
Maintainer-email: EnkaliPrime <support@enkaliprime.com>
License-Expression: MIT
Project-URL: Homepage, https://enkaliprime.com
Project-URL: Documentation, https://api.enkaliprime.com/docs
Project-URL: Repository, https://github.com/enkaliprime/python-sdk
Project-URL: Issues, https://github.com/enkaliprime/python-sdk/issues
Keywords: cli,chat,ai,enkaliprime,chatbot,command-line
Classifier: Development Status :: 4 - Beta
Classifier: Intended Audience :: End Users/Desktop
Classifier: Operating System :: OS Independent
Classifier: Programming Language :: Python :: 3
Classifier: Programming Language :: Python :: 3.8
Classifier: Programming Language :: Python :: 3.9
Classifier: Programming Language :: Python :: 3.10
Classifier: Programming Language :: Python :: 3.11
Classifier: Programming Language :: Python :: 3.12
Classifier: Programming Language :: Python :: 3.13
Classifier: Topic :: Communications :: Chat
Classifier: Topic :: Utilities
Classifier: Typing :: Typed
Requires-Python: >=3.8
License-File: LICENSE
Requires-Dist: enkaliprime>=1.2.0
Requires-Dist: typer>=0.9.0
Requires-Dist: rich>=13.0.0
Requires-Dist: keyring>=24.0.0
Requires-Dist: click>=8.0.0
Requires-Dist: psutil>=5.9.0
Requires-Dist: requests>=2.25.0
Requires-Dist: pyperclip>=1.8.0
Provides-Extra: dev
Requires-Dist: pytest>=7.0.0; extra == "dev"
Requires-Dist: pytest-asyncio>=0.21.0; extra == "dev"
Requires-Dist: black>=23.0.0; extra == "dev"
Requires-Dist: isort>=5.12.0; extra == "dev"
Requires-Dist: mypy>=1.0.0; extra == "dev"
Requires-Dist: ruff>=0.0.280; extra == "dev"
Dynamic: license-file
